workflows/__init__.py
workflows/decorators.py
workflows/errors.py
workflows/events.py
workflows/handler.py
workflows/py.typed
workflows/resource.py
workflows/retry_policy.py
workflows/types.py
workflows/utils.py
workflows/workflow.py
workflows/client/__init__.py
workflows/client/client.py
workflows/context/__init__.py
workflows/context/context.py
workflows/context/context_types.py
workflows/context/py.typed
workflows/context/serializers.py
workflows/context/state_store.py
workflows/context/utils.py
workflows/plugins/basic.py
workflows/protocol/__init__.py
workflows/protocol/serializable_events.py
workflows/runtime/broker.py
workflows/runtime/control_loop.py
workflows/runtime/workflow_registry.py
workflows/runtime/types/_identity_weak_ref.py
workflows/runtime/types/commands.py
workflows/runtime/types/internal_state.py
workflows/runtime/types/plugin.py
workflows/runtime/types/results.py
workflows/runtime/types/step_function.py
workflows/runtime/types/ticks.py
workflows/server/__init__.py
workflows/server/__main__.py
workflows/server/abstract_workflow_store.py
workflows/server/memory_workflow_store.py
workflows/server/representation_utils.py
workflows/server/server.py
workflows/server/sqlite/__init__.py
workflows/server/sqlite/migrate.py
workflows/server/sqlite/sqlite_workflow_store.py
workflows/server/sqlite/migrations/0001_init.sql
workflows/server/sqlite/migrations/0002_extend_handlers.sql
workflows/server/sqlite/migrations/__init__.py
workflows/server/static/index.html
workflows/testing/__init__.py
workflows/testing/runner.py
llama_index_workflows-2.11.2.dist-info/METADATA
llama_index_workflows-2.11.2.dist-info/WHEEL
llama_index_workflows-2.11.2.dist-info/RECORD
